KPTE/KPTE.py
KPTE/PipReqs.py
KPTE/__init__.py
KPTE/Data/Python.7z
KPTE/Data/icon.ico
KPTE-1.3.9.dist-info/LICENSE
KPTE-1.3.9.dist-info/METADATA
KPTE-1.3.9.dist-info/WHEEL
KPTE-1.3.9.dist-info/entry_points.txt
KPTE-1.3.9.dist-info/top_level.txt
KPTE-1.3.9.dist-info/RECORD
