Metadata-Version: 2.1
Name: KPTE
Version: 1.3.9
Summary: KPTE用于将.py文件转换为.exe可执行文件
Home-page: https://github.com/kaixin168sxz/KPTE
Author: Kaixin
Author-email: kaixin168KX@163.com
Classifier: Programming Language :: Python :: 3
Classifier: License :: OSI Approved :: MIT License
Classifier: Operating System :: OS Independent
Requires-Python: >=3.8
License-File: LICENSE
